README.rst
counterparts.py
setup.py
counterparts.egg-info/PKG-INFO
counterparts.egg-info/SOURCES.txt
counterparts.egg-info/dependency_links.txt
counterparts.egg-info/entry_points.txt
counterparts.egg-info/top_level.txt
tests/__init__.py
tests/test_counterparts.py
tests/counterparts_data/conf-0
tests/counterparts_data/conf-1
tests/counterparts_data/conf-1-in-default
tests/counterparts_data/conf-1-overrides-default
tests/counterparts_data/conf-2
tests/counterparts_data/conf-2-with-include
tests/counterparts_data/conf-2-without-include
tests/counterparts_data/conf-hostname
tests/counterparts_data/conf-include-logging
tests/counterparts_data/conf-include-more
tests/counterparts_data/conf-include-still-more
tests/counterparts_data/conf-include-still-more-past-more
tests/counterparts_data/conf-map-home
tests/counterparts_data/conf-null
tests/counterparts_data/conf-peer-0
tests/counterparts_data/conf-recursive